LICENSE
README.rst
setup.py
pmcpy/__init__.py
pmcpy/pmcpy.py
pmcpy.egg-info/PKG-INFO
pmcpy.egg-info/SOURCES.txt
pmcpy.egg-info/dependency_links.txt
pmcpy.egg-info/requires.txt
pmcpy.egg-info/top_level.txt