Metadata-Version: 2.1
Name: pmcpy
Version: 0.0.2
Summary: A Python package for PartMC post-processing
Home-page: https://github.com/zzheng93/pmcpy
Author: Zhonghua Zheng
Author-email: zhonghua.zheng@outlook.com
License: MIT
Platform: UNKNOWN
Classifier: Development Status :: 2 - Pre-Alpha
Classifier: Intended Audience :: Science/Research
Classifier: License :: OSI Approved :: MIT License
Classifier: Natural Language :: English
Classifier: Operating System :: OS Independent
Classifier: Programming Language :: Python :: 3
Classifier: Topic :: Scientific/Engineering :: Atmospheric Science
License-File: LICENSE
